coperator
