Metadata-Version: 1.0
Name: coperator
Version: 1.1.12
Summary: Custom operators for python
Home-page: https://gitlab.com/jecjimenezgi/coperator.git
Author: Jean Carlo Jimenez Giraldo
Author-email: mandalarotation@gmail.com
License: MIT
Platform: UNKNOWN
